{
  "id": "pf2e-wands-and-scrolls",
  "title": "PF2e Wands And Scrolls",
  "description": "A module that automatically adds your wands and scroll spells to your spellcasting tab",
  "version": "1.0.0",
  "library": "false",
  "manifestPlusVersion": "1.2.0",
  "compatibility": {
    "minimum": 11,
    "verified": 11
  },
  "authors": [
    {
      "name": "Rowiz49",
      "url": "https://github.com/Rowiz49"
    }
  ],
  "relationships": {
    "systems": [
      {
        "id": "pf2e",
        "type": "system",
        "compatibility": {
          "minimum": "5.12.0"
        }
      }
    ],
    "requires": [
      {
        "id": "lib-wrapper",
        "type": "module",
        "compatibility": {
          "minimum": "1",
          "verified": "1.12.13.0"
        }
      }
    ]
  },
  "esmodules": [
    "scripts/hooks.js"
  ],
  "styles": [
    "styles/module.css"
  ],
  "languages": [],
  "flags": {},
  "url": "",
  "manifest": "",
  "download": "",
  "license": "LICENSE",
  "readme": "README.md"
}